PAPyA/Rank.py
PAPyA/Ranker.py
PAPyA/__init__.py
PAPyA/best_of_k.py
PAPyA/config_loader.py
PAPyA/file_reader.py
PAPyA/get_ranks.py
PAPyA/joinTuple.py
PAPyA/kendall_index.py
PAPyA/nsga2.py
PAPyA-1.1.6.dist-info/METADATA
PAPyA-1.1.6.dist-info/WHEEL
PAPyA-1.1.6.dist-info/top_level.txt
PAPyA-1.1.6.dist-info/RECORD
