Metadata-Version: 2.1
Name: PAPyA
Version: 1.1.6
Summary: A library for performance analysis of sql based RDF graph processing systems
Author: Mohammed Ragab, Adam Satria Adidarma, Riccardo Tommasini
Author-email: mohammed.ragab@ut.ee, adam.19051@mhs.its.ac.id, riccardo.tommasini@ut.ee
License: UNKNOWN
Keywords: python,benchmarking,rdf systems,big data,apache spark
Platform: UNKNOWN
Classifier: Development Status :: 5 - Production/Stable
Classifier: Intended Audience :: Developers
Classifier: Programming Language :: Python :: 3
Classifier: Operating System :: Unix
Classifier: Operating System :: MacOS :: MacOS X
Classifier: Operating System :: Microsoft :: Windows
Requires-Dist: matplotlib
Requires-Dist: notebook
Requires-Dist: PyYAML
Requires-Dist: pandas
Requires-Dist: scipy
Requires-Dist: plotly
Requires-Dist: seaborn
